{
  "kind": "singleType",
  "collectionName": "chartered_flights",
  "info": {
    "singularName": "chartered-flight",
    "pluralName": "chartered-flights",
    "displayName": "Chartered Flight",
    "description": ""
  },
  "options": {
    "draftAndPublish": true
  },
  "pluginOptions": {},
  "attributes": {
    "seo": {
      "type": "component",
      "repeatable": false,
      "component": "seo.seo"
    },
    "metaData": {
      "type": "component",
      "repeatable": false,
      "component": "meta-data.meta-data"
    },
    "pageTitle": {
      "type": "component",
      "repeatable": false,
      "component": "elements.title-with-image"
    },
    "charteredFlightPage": {
      "type": "dynamiczone",
      "components": [
        "common.accordian",
        "elements.title-with-description"
      ]
    },
    "charteredFlightTab": {
      "type": "dynamiczone",
      "components": [
        "chartered-flights-page.pricing-tab",
        "chartered-flights-page.fleet-tab",
        "chartered-flights-page.destination"
      ]
    }
  }
}
