{
  "kind": "singleType",
  "collectionName": "aerospace_part_sales",
  "info": {
    "singularName": "aerospace-part-sale",
    "pluralName": "aerospace-part-sales",
    "displayName": "[AERO] - PartSale",
    "description": ""
  },
  "options": {
    "draftAndPublish": true
  },
  "pluginOptions": {},
  "attributes": {
    "title": {
      "type": "string"
    },
    "aerospaceSalesItem": {
      "type": "relation",
      "relation": "oneToMany",
      "target": "api::aerospace-sales-item.aerospace-sales-item"
    },
    "viewMore": {
      "type": "component",
      "component": "elements.button",
      "repeatable": false
    },
    "showOtherSaleItems": {
      "type": "boolean",
      "default": false
    },
    "partsEnquiryForm": {
      "type": "component",
      "component": "further-questions.contact-form",
      "repeatable": false
    },
    "seo": {
      "type": "component",
      "component": "seo.seo",
      "repeatable": false
    }
  }
}
